django_colors/__init__.py
django_colors/apps.py
django_colors/color_definitions.py
django_colors/conftest.py
django_colors/field_type.py
django_colors/fields.py
django_colors/models.py
django_colors/settings.py
django_colors/widgets.py
django_colors/templates/color_select.html
django_colors/templates/color_select_option.html
django_colors/tests/settings.py
django_colors/tests/test_apps.py
django_colors/tests/test_color_definitions.py
django_colors/tests/test_field_type.py
django_colors/tests/test_fields.py
django_colors/tests/test_models.py
django_colors/tests/test_settings.py
django_colors/tests/test_widgets.py
django_colors-1.2.3.dist-info/METADATA
django_colors-1.2.3.dist-info/WHEEL
django_colors-1.2.3.dist-info/licenses/LICENSE
django_colors-1.2.3.dist-info/RECORD
