Metadata-Version: 2.4
Name: django-colors
Version: 1.2.3
Summary: An application to assist with css framework color selections.
License-File: LICENSE
Classifier: Development Status :: 4 - Beta
Classifier: Framework :: Django
Classifier: Programming Language :: Python
Requires-Python: >=3.11
Requires-Dist: django>=4.2
Provides-Extra: dev
Requires-Dist: djlint; extra == 'dev'
Requires-Dist: pre-commit; extra == 'dev'
Requires-Dist: pytest; extra == 'dev'
Requires-Dist: pytest-cov; extra == 'dev'
Requires-Dist: pytest-django; extra == 'dev'
Requires-Dist: ruff; extra == 'dev'
